{
  "literalComponents": [
    {
      "id": "lc_2b2_ps1",
      "name": "PS1",
      "componentId": "component_power_supply_1779600000005",
      "superiors": [],
      "variableOverrides": {
        "energised": true
      },
      "_canvas": {
        "x": 656,
        "y": -110
      }
    },
    {
      "id": "lc_2b2_wire_a",
      "name": "Wire_A",
      "componentId": "component_wire_1779700000001",
      "superiors": [
        "lc_2b2_ps1"
      ],
      "variableOverrides": {},
      "_canvas": {
        "x": 732,
        "y": -62
      }
    },
    {
      "id": "lc_2b2_sw_enable",
      "name": "SW_Enable",
      "componentId": "component_switch_1779700000002",
      "superiors": [
        "lc_2b2_wire_a"
      ],
      "variableOverrides": {},
      "_canvas": {
        "x": 804,
        "y": -126
      }
    },
    {
      "id": "lc_2b2_wire_b",
      "name": "Wire_B",
      "componentId": "component_wire_1779700000001",
      "superiors": [
        "lc_2b2_sw_enable"
      ],
      "variableOverrides": {},
      "_canvas": {
        "x": 804,
        "y": -38
      }
    },
    {
      "id": "lc_2b2_inlet",
      "name": "Inlet",
      "componentId": "component_1779500000005",
      "superiors": [],
      "variableOverrides": {
        "flow.colour": "#2a7abf",
        "flow.composition": [
          {
            "name": "process_water",
            "colour": "#2a7abf",
            "mole_fraction": 1
          }
        ]
      },
      "_canvas": {
        "x": 8,
        "y": 82
      }
    },
    {
      "id": "lc_2b2_pipe_a",
      "name": "Pipe_A",
      "componentId": "component_pipe_1779600000001",
      "superiors": [
        "lc_2b2_inlet"
      ],
      "variableOverrides": {
        "resistance": 0.02
      },
      "_canvas": {
        "x": 108,
        "y": 82
      }
    },
    {
      "id": "lc_2b2_v1",
      "name": "V1",
      "componentId": "component_1779399245576",
      "superiors": [
        "lc_2b2_pipe_a"
      ],
      "variableOverrides": {},
      "_canvas": {
        "x": 216,
        "y": 90
      }
    },
    {
      "id": "lc_2b2_pipe_b",
      "name": "Pipe_B",
      "componentId": "component_pipe_1779600000001",
      "superiors": [
        "lc_2b2_v1"
      ],
      "variableOverrides": {
        "resistance": 0.02
      },
      "_canvas": {
        "x": 324,
        "y": 82
      }
    },
    {
      "id": "lc_2b2_p1",
      "name": "P1",
      "componentId": "component_1779500000001",
      "superiors": [
        "lc_2b2_pipe_b"
      ],
      "variableOverrides": {
        "outlet_pressure": 110
      },
      "_canvas": {
        "x": 432,
        "y": 71
      }
    },
    {
      "id": "lc_2b2_pipe_c",
      "name": "Pipe_C",
      "componentId": "component_pipe_1779600000001",
      "superiors": [
        "lc_2b2_p1"
      ],
      "variableOverrides": {
        "resistance": 0.02
      },
      "_canvas": {
        "x": 540,
        "y": 82
      }
    },
    {
      "id": "lc_2b2_v2",
      "name": "V2",
      "componentId": "component_1779399245576",
      "superiors": [
        "lc_2b2_pipe_c"
      ],
      "variableOverrides": {},
      "_canvas": {
        "x": 672,
        "y": 90
      }
    },
    {
      "id": "lc_2b2_pipe_d",
      "name": "Pipe_D",
      "componentId": "component_pipe_1779600000001",
      "superiors": [
        "lc_2b2_v2"
      ],
      "variableOverrides": {
        "resistance": 0.02
      },
      "_canvas": {
        "x": 708,
        "y": 178
      }
    },
    {
      "id": "lc_2b2_ecv1",
      "name": "ECV1",
      "componentId": "component_ecv_1779600000003",
      "superiors": [
        "lc_2b2_pipe_d",
        "lc_2b2_wire_b"
      ],
      "variableOverrides": {
        "signal": 100,
        "fail_open": false,
        "auto": false
      },
      "_canvas": {
        "x": 792,
        "y": 64.5
      }
    },
    {
      "id": "lc_2b2_pipe_e",
      "name": "Pipe_E",
      "componentId": "component_pipe_1779600000001",
      "superiors": [
        "lc_2b2_ecv1"
      ],
      "variableOverrides": {
        "resistance": 0.02
      },
      "_canvas": {
        "x": 900,
        "y": 82
      }
    },
    {
      "id": "lc_2b2_h1",
      "name": "H1",
      "componentId": "component_1779500000003",
      "superiors": [
        "lc_2b2_pipe_e"
      ],
      "variableOverrides": {},
      "_canvas": {
        "x": 1032,
        "y": 85.5
      }
    },
    {
      "id": "lc_2b2_pipe_f",
      "name": "Pipe_F",
      "componentId": "component_pipe_1779600000001",
      "superiors": [
        "lc_2b2_h1"
      ],
      "variableOverrides": {
        "resistance": 0.02
      },
      "_canvas": {
        "x": 1140,
        "y": 82
      }
    },
    {
      "id": "lc_2b2_v3",
      "name": "V3",
      "componentId": "component_1779399245576",
      "superiors": [
        "lc_2b2_pipe_f"
      ],
      "variableOverrides": {},
      "_canvas": {
        "x": 1248,
        "y": 90
      }
    },
    {
      "id": "lc_2b2_pipe_g",
      "name": "Pipe_G",
      "componentId": "component_pipe_1779600000001",
      "superiors": [
        "lc_2b2_v3"
      ],
      "variableOverrides": {
        "resistance": 0.02
      },
      "_canvas": {
        "x": 1356,
        "y": 82
      }
    },
    {
      "id": "lc_2b2_outlet",
      "name": "Outlet",
      "componentId": "component_1779500000006",
      "superiors": [
        "lc_2b2_pipe_g"
      ],
      "variableOverrides": {},
      "_canvas": {
        "x": 1472,
        "y": 82
      }
    }
  ]
}